lib_hero/model/__init__.py
lib_hero/model/dto.py
lib_hero/model/models.py
lib_hero/repository/__init__.py
lib_hero/repository/base.py
lib_hero/service/__init__.py
lib_hero/service/base.py
lib_hero/util/__init__.py
lib_hero/util/database.py
herolibmagnagomatheus-0.1.1.dist-info/METADATA
herolibmagnagomatheus-0.1.1.dist-info/WHEEL
herolibmagnagomatheus-0.1.1.dist-info/top_level.txt
herolibmagnagomatheus-0.1.1.dist-info/RECORD
